MANIFEST.in
readme.md
requirements.txt
setup.cfg
setup.py
Facebook/Generate.py
Facebook/Send.py
Facebook/__init__.py
Facebook/exception.py
Facebook/generate.py
Facebook/handlers.py
Facebook/message.py
Facebook/send.py
Facebook/webhook.py
Facebook_PyBot.egg-info/PKG-INFO
Facebook_PyBot.egg-info/SOURCES.txt
Facebook_PyBot.egg-info/dependency_links.txt
Facebook_PyBot.egg-info/requires.txt
Facebook_PyBot.egg-info/top_level.txt
examples/echo.py
examples/userInfo.py