Metadata-Version: 1.1
Name: Facebook-PyBot
Version: 0.8b4
Summary: This is an Unofficial Facebook bot API in python. Facebook Bots can be build using this library.
Home-page: https://github.com/hundredeir/Facebook_PyBot
Author: hundredeir
Author-email: hundredeir@protonmail.com
License: GPL3
Keywords: Facebook Bot API Wrapper Python
Platform: UNKNOWN
Classifier: Development Status :: 4 - Beta
Classifier: Intended Audience :: Developers
Classifier: License :: OSI Approved :: GNU General Public License v3 (GPLv3)
Classifier: Operating System :: OS Independent
Classifier: Topic :: Software Development :: Libraries :: Python Modules
Classifier: Topic :: Communications :: Chat
Classifier: Topic :: Internet
Classifier: Programming Language :: Python
